polymorphic/__init__.py
polymorphic/apps.py
polymorphic/base.py
polymorphic/deletion.py
polymorphic/managers.py
polymorphic/models.py
polymorphic/query.py
polymorphic/query_translate.py
polymorphic/related_descriptors.py
polymorphic/showfields.py
polymorphic/utils.py
polymorphic/admin/__init__.py
polymorphic/admin/childadmin.py
polymorphic/admin/filters.py
polymorphic/admin/forms.py
polymorphic/admin/generic.py
polymorphic/admin/helpers.py
polymorphic/admin/inlines.py
polymorphic/admin/parentadmin.py
polymorphic/contrib/__init__.py
polymorphic/contrib/extra_views.py
polymorphic/contrib/guardian.py
polymorphic/contrib/drf/LICENSE
polymorphic/contrib/drf/__init__.py
polymorphic/contrib/drf/serializers.py
polymorphic/formsets/__init__.py
polymorphic/formsets/generic.py
polymorphic/formsets/models.py
polymorphic/formsets/utils.py
polymorphic/locale/en/LC_MESSAGES/django.po
polymorphic/locale/es/LC_MESSAGES/django.po
polymorphic/locale/fr/LC_MESSAGES/django.po
polymorphic/static/polymorphic/css/polymorphic_inlines.css
polymorphic/static/polymorphic/js/polymorphic_inlines.js
polymorphic/templates/admin/polymorphic/add_type_form.html
polymorphic/templates/admin/polymorphic/change_form.html
polymorphic/templates/admin/polymorphic/delete_confirmation.html
polymorphic/templates/admin/polymorphic/object_history.html
polymorphic/templates/admin/polymorphic/edit_inline/stacked.html
polymorphic/templatetags/__init__.py
polymorphic/templatetags/polymorphic_admin_tags.py
polymorphic/templatetags/polymorphic_formset_tags.py
django_polymorphic-4.10.5.dist-info/METADATA
django_polymorphic-4.10.5.dist-info/WHEEL
django_polymorphic-4.10.5.dist-info/licenses/LICENSE
django_polymorphic-4.10.5.dist-info/licenses/src/polymorphic/contrib/drf/LICENSE
django_polymorphic-4.10.5.dist-info/RECORD
