Metadata-Version: 2.4
Name: django-polymorphic
Version: 4.10.5
Summary: Seamless polymorphic inheritance for Django models.
Project-URL: Download, https://github.com/jazzband/django-polymorphic/tarball/master
Project-URL: Documentation, https://django-polymorphic.readthedocs.io
Project-URL: Homepage, https://github.com/jazzband/django-polymorphic
Project-URL: Repository, https://github.com/jazzband/django-polymorphic
Project-URL: Issues, https://github.com/jazzband/django-polymorphic/issues
Project-URL: Changelog, https://django-polymorphic.readthedocs.io/en/stable/changelog/index.html
Project-URL: Code_of_Conduct, https://jazzband.co/about/conduct
Author-email: Bert Constantin <bert.constantin@gmx.de>, Diederik van der Boor <vdboor@edoburu.nl>, Christopher Glass <tribaal@ubuntu.com>
Maintainer-email: Brian Kohan <bckohan@gmail.com>
License-Expression: BSD-3-Clause
License-File: LICENSE
License-File: src/polymorphic/contrib/drf/LICENSE
Keywords: django,django-admin,django-formsets,django-orm,model,polymorphic,polymorphism
Classifier: Development Status :: 5 - Production/Stable
Classifier: Environment :: Web Environment
Classifier: Framework :: Django
Classifier: Framework :: Django :: 4.2
Classifier: Framework :: Django :: 5.1
Classifier: Framework :: Django :: 5.2
Classifier: Framework :: Django :: 6.0
Classifier: Intended Audience :: Developers
Classifier: License :: OSI Approved :: BSD License
Classifier: Natural Language :: English
Classifier: Operating System :: OS Independent
Classifier: Programming Language :: Python :: 3
Classifier: Programming Language :: Python :: 3 :: Only
Classifier: Programming Language :: Python :: 3.10
Classifier: Programming Language :: Python :: 3.11
Classifier: Programming Language :: Python :: 3.12
Classifier: Programming Language :: Python :: 3.13
Classifier: Programming Language :: Python :: 3.14
Classifier: Topic :: Database
Classifier: Topic :: Internet :: WWW/HTTP
Classifier: Topic :: Internet :: WWW/HTTP :: Site Management
Classifier: Topic :: Software Development :: Libraries
Classifier: Topic :: Software Development :: Libraries :: Python Modules
Requires-Python: <4.0,>=3.10
Requires-Dist: django>=4.2
